{
  "simplified": "䰜",
  "traditional": "䰜",
  "pinyin": "nil",
  "english": "'cauldron'",
  "etymology": {
    "type": "ideogrammic compound",
    "description": "phonetic 鬳(鬳) + semantic 瓦(瓦)",
    "interpretation": "The character combines the phonetic element 鬳 (yǎn, 'cooking vessel') with the semantic element 瓦 (wǎ, 'earthenware'), which represents something made from clay or pottery, leading to the meaning of a 'cauldron'.",
    "simplification": ""
  },
  "parts": [
    {
      "char": "鬳",
      "trad": "鬳",
      "pinyin": "yǎn",
      "english": "cooking vessel"
    },
    {
      "char": "瓦",
      "trad": "瓦",
      "pinyin": "wǎ",
      "english": "earthenware"
    }
  ],
  "in_contemporary_usage": false,
  "examples": [
    {
      "chinese": "在历史书中出现这个字(在歷史書中出現這個字)。",
      "pinyin": "Zài lìshǐ shū zhōng chūxiàn zhège zì.",
      "english": "This character appears in historical texts."
    },
    {
      "chinese": "古代有许多种类的鬲(古代有許多種類的鬲)。",
      "pinyin": "Gǔdài yǒu xǔduō zhǒnglèi de gě.",
      "english": "There were many kinds of cauldrons in ancient times."
    }
  ]
}
