{
  "simplified": "來",
  "traditional": "來",
  "pinyin": "lái",
  "english": "to come",
  "etymology": {
    "type": "pictogram",
    "description": "Depicts wheat with the middle line representing the ear, upward lines for leaves, and downward lines for stem and roots.",
    "interpretation": "The character visually represents wheat, which historically symbolizes nourishment and growth. This connection is reflected in its use for 'to come', suggesting a bringing forth or arrival of sustenance.",
    "simplification": ""
  },
  "parts": [],
  "in_contemporary_usage": true,
  "examples": [
    {
      "chinese": "他要來了(他要來了)，我们应该准备好(我們應該準備好)。",
      "pinyin": "tā yào lái le, wǒmen yīnggāi zhǔnbèi hǎo.",
      "english": "He is coming, we should be ready."
    },
    {
      "chinese": "请她來(請她來)！",
      "pinyin": "qǐng tā lái!",
      "english": "Please have her come!"
    }
  ]
}
