{
  "simplified": "喿",
  "traditional": "喿",
  "pinyin": "zào",
  "english": "used phonetically",
  "etymology": {
    "type": "ideogrammic compound",
    "description": "品(品) (pǐn, \"three mouths\") + 木(木) (mù, \"tree\") = chirping of birds in a tree -> original form of 噪(噪) (zào, \"noisy\")",
    "interpretation": "喿(喿) (zào, \"used phonetically\") combines the concept of multiple mouths with a tree to depict the chirping sounds of birds, emphasizing the idea of collective noise. It later became the original form of 噪(噪) (zào, \"noisy\") which directly relates to noise made by mouths.",
    "simplification": ""
  },
  "parts": [
    {
      "char": "品",
      "trad": "品",
      "pinyin": "pǐn",
      "english": "three mouths"
    },
    {
      "char": "木",
      "trad": "木",
      "pinyin": "mù",
      "english": "tree"
    },
    {
      "char": "噪",
      "trad": "噪",
      "pinyin": "zào",
      "english": "noisy"
    }
  ],
  "in_contemporary_usage": false,
  "examples": []
}
