{
  "simplified": "夐",
  "traditional": "夐",
  "pinyin": "xiòng",
  "english": "eminent",
  "etymology": {
    "type": "phono-semantic compound",
    "description": "穴(穴, \"cave\") + 目(目, \"eye\") + 支(支, \"hand holding a stick\") = authority asserted -> eminent",
    "interpretation": "The combination of a cave or closed space with an eye suggests observation or vigilance, while the hand holding a stick implies authority or guidance. Together, these motifs imply a sense of prominence or eminence, as a figure who oversees and controls from a place of power.",
    "simplification": ""
  },
  "parts": [
    {
      "char": "穴",
      "trad": "穴",
      "pinyin": "xué",
      "english": "cave"
    },
    {
      "char": "目",
      "trad": "目",
      "pinyin": "mù",
      "english": "eye"
    },
    {
      "char": "支",
      "trad": "支",
      "pinyin": "zhī",
      "english": "hand holding a stick"
    }
  ],
  "in_contemporary_usage": false,
  "examples": []
}
