{
  "simplified": "小时候",
  "traditional": "小時候",
  "pinyin": "xiǎoshíhou",
  "english": "childhood",
  "etymology": {
    "type": "compound word",
    "description": "小(小) (xiǎo, \"small\") + 時(時) (shí, \"time\") + 候(候) (hòu, \"time period\") = phase of smallness -> childhood",
    "interpretation": "小時候 refers to the time period when one is small, or in other words, one's childhood. It emphasizes the phase of life characterized by being young and small.",
    "simplification": ""
  },
  "parts": [
    {
      "char": "小",
      "trad": "小",
      "pinyin": "xiǎo",
      "english": "small"
    },
    {
      "char": "時候",
      "trad": "時候",
      "pinyin": "shíhòu",
      "english": "time period; time; moment; length of time"
    }
  ],
  "in_contemporary_usage": true,
  "examples": [
    {
      "chinese": "小时候(小時候)，我常常在公园玩耍(我常常在公園玩耍)。",
      "pinyin": "Xiǎoshíhou, wǒ chángcháng zài gōngyuán wánshuǎ.",
      "english": "During childhood, I often played in the park."
    },
    {
      "chinese": "她小时候(她小時候)喜欢听爷爷讲故事(喜歡聽爺爺講故事)。",
      "pinyin": "Tā xiǎoshíhou xǐhuan tīng yéye jiǎng gùshì.",
      "english": "She liked to listen to grandpa tell stories during her childhood."
    },
    {
      "chinese": "我的小时候(我的小時候)充满了快乐和笑声(充滿了快樂和笑聲)。",
      "pinyin": "Wǒ de xiǎoshíhou chōngmǎnle kuàilè hé xiàoshēng.",
      "english": "My childhood was filled with joy and laughter."
    }
  ]
}
