{
  "simplified": "悤",
  "traditional": "悤",
  "pinyin": "cōng",
  "english": "clever",
  "etymology": {
    "type": "phono-semantic compound",
    "description": "心(心) (xīn, \"heart\") + 囱(囱) (cōng) = original form had heart with dot -> evolved to include 囱 pattern -> clever -> preserved in 聰(聰) (cōng, \"intelligent\")",
    "interpretation": "The character 悤 originally depicted a heart with a dot on top, symbolizing intelligence, and evolved into a patterned shape. The notion of intelligence as holes on the heart is a traditional concept, leading to the character 聰(聰) (cōng, \"intelligent\"). Over time, 悤 acquired meanings associated with fast learning or hasty action.",
    "simplification": ""
  },
  "parts": [
    {
      "char": "心",
      "trad": "心",
      "pinyin": "xīn",
      "english": "heart"
    },
    {
      "char": "囱",
      "trad": "囱",
      "pinyin": "cōng",
      "english": "pattern"
    },
    {
      "char": "聰",
      "trad": "聰",
      "pinyin": "cōng",
      "english": "intelligent"
    }
  ],
  "in_contemporary_usage": false,
  "examples": []
}
