{
  "simplified": "扫码",
  "traditional": "扫码",
  "pinyin": "sǎomǎ",
  "english": "scan a code",
  "etymology": {
    "type": "compound word",
    "description": "扫(sweep/scan) + 码(code/number) = scan a code.",
    "interpretation": "Common in modern tech and commerce for scanning QR or barcodes, often with a smartphone. Usually implies actions like payment, login, registration, or access verification.",
    "simplification": "Both characters were simplified in the PRC to reduce strokes: 掃→扫 by simplifying the right component; 碼→码 by using the simplified 马 and a simpler left form, matching widespread digital-era usage."
  },
  "parts": [
    {
      "char": "扫",
      "trad": "掃",
      "pinyin": "sǎo",
      "english": "to sweep; to scan; to brush over; to eliminate"
    },
    {
      "char": "码",
      "trad": "碼",
      "pinyin": "mǎ",
      "english": "code; number; yard (unit); to stack/pile"
    }
  ],
  "examples": [
    {
      "chinese": "请先扫码支付(請先掃碼支付)。",
      "pinyin": "Qǐng xiān sǎomǎ zhīfù.",
      "english": "Please scan the code to pay first."
    },
    {
      "chinese": "进门前(進門前)，保安让我扫码登记(保安讓我掃碼登記)。",
      "pinyin": "Jìn mén qián, bǎo'ān ràng wǒ sǎomǎ dēngjì.",
      "english": "Before entering, the guard asked me to scan the code to register."
    },
    {
      "chinese": "打开相机对准二维码(打開相機對準二維碼)，轻轻一扫就能完成登录(輕輕一掃就能完成登錄)。",
      "pinyin": "Dǎkāi xiàngjī duìzhǔn èrwéimǎ, qīngqīng yī sǎo jiù néng wánchéng dēnglù.",
      "english": "Open the camera and aim at the QR code; a quick scan can complete the login."
    }
  ]
}
