{
  "simplified": "旧",
  "traditional": "舊",
  "pinyin": "jiù",
  "english": "old; past; worn",
  "etymology": {
    "type": "phono-semantic compound",
    "description": "semantic 雈(雈) (huán, 'owl') + phonetic 臼(臼) (jiù) -> originally 'a type of owl', borrowed for phonetic similarity to 'old'",
    "interpretation": "The character 舊(舊) (jiù, 'old') combines the semantic component 雈(雈) (huán, 'owl') with the phonetic component 臼(臼) (jiù, 'mortar'). It was initially used to represent a type of owl, which was later borrowed for its sound to denote 'old', associating the unchanging nature of the owl with the concept of 'oldness' or the passage of time.",
    "simplification": "旧 is the simplified form, reducing complexity from 舊 by removing the semantic component 雈(雈) (huán, 'owl') while preserving the sound with 臼(臼) (jiù)."
  },
  "parts": [
    {
      "char": "雈",
      "trad": "雈",
      "pinyin": "huán",
      "english": "owl"
    },
    {
      "char": "臼",
      "trad": "臼",
      "pinyin": "jiù",
      "english": "mortar"
    }
  ],
  "in_contemporary_usage": true,
  "examples": [
    {
      "chinese": "这本书很旧(這本書很舊)。",
      "pinyin": "Zhè běn shū hěn jiù.",
      "english": "This book is very old."
    },
    {
      "chinese": "他穿着旧衬衫(他穿著舊襯衫)，看起来有些疲倦(看起來有些疲倦)。",
      "pinyin": "Tā chuānzhe jiù chènshān, kàn qǐlái yǒu xiē píjuàn.",
      "english": "He is wearing a worn shirt and looks a bit tired."
    },
    {
      "chinese": "她时常怀念过去的旧时光(她時常懷念過去的舊時光)。",
      "pinyin": "Tā shícháng huáiniàn guòqù de jiù shíguāng.",
      "english": "She often reminisces about the old times."
    }
  ]
}
