{
  "simplified": "材",
  "traditional": "材",
  "pinyin": "cái",
  "english": "material; timber",
  "etymology": {
    "type": "phono-semantic compound",
    "description": "semantic 木(木) (mù, \"tree\") + phonetic 才(才) (cái, \"talent (phonetic)\") -> material; timber",
    "interpretation": "The character combines 木(木) (mù, \"tree\") as the semantic component, representing trees or wood, with 才(才) (cái), which provides the phonetic element. The combination indicates timber as processed wood material, derived from trees, and this extends metaphorically to 'material' in general as a resource or substance that can be worked with, much like wood.",
    "simplification": ""
  },
  "parts": [
    {
      "char": "木",
      "trad": "木",
      "pinyin": "mù",
      "english": "tree"
    },
    {
      "char": "才",
      "trad": "才",
      "pinyin": "cái",
      "english": "talent"
    }
  ],
  "in_contemporary_usage": true,
  "examples": [
    {
      "chinese": "这座房子是用优质的木材建造的(這座房子是用優質的木材建造的)。",
      "pinyin": "Zhè zuò fángzi shì yòng yōuzhì de mùcái jiànzào de.",
      "english": "This house is built with high-quality timber."
    },
    {
      "chinese": "他具备成为优秀工程师的材料(他具備成為優秀工程師的材料)。",
      "pinyin": "Tā jùbèi chéngwéi yōuxiù gōngchéngshī de cáiliào.",
      "english": "He has the material to become an excellent engineer."
    }
  ]
}
