{
  "simplified": "湘",
  "traditional": "湘",
  "pinyin": "xiāng",
  "english": "Xiang River",
  "etymology": {
    "type": "phono-semantic compound",
    "description": "semantic 水(水) (shuǐ, \"water\") + phonetic 相(相) (xiāng) -> Xiang River",
    "interpretation": "The character 湘(xiāng) is formed by combining the semantic component 水(shuǐ, \"water\"), denoting a river or water-related context, with the phonetic component 相(xiāng), which provides the pronunciation. This combination specifically refers to the Xiang River in China, indicating a water body by its name.",
    "simplification": ""
  },
  "parts": [
    {
      "char": "水",
      "trad": "水",
      "pinyin": "shuǐ",
      "english": "water"
    },
    {
      "char": "相",
      "trad": "相",
      "pinyin": "xiāng",
      "english": "mutual; appearance"
    }
  ],
  "in_contemporary_usage": true,
  "examples": [
    {
      "chinese": "湘江蜿蜒流过城市和田野(湘江蜿蜒流過城市和田野)。",
      "pinyin": "Xiāng jiāng wānyán liú guò chéngshì hé tiányě.",
      "english": "The Xiang River winds through cities and fields."
    },
    {
      "chinese": "许多人来到湘江边野餐(許多人來到湘江邊野餐)。",
      "pinyin": "Xǔduō rén lái dào Xiāng jiāng biān yěcān.",
      "english": "Many people come to the banks of the Xiang River for a picnic."
    },
    {
      "chinese": "湘水之上，舟影摇曳(湘水之上，舟影搖曳)。",
      "pinyin": "Xiāng shuǐ zhī shàng, zhōu yǐng yáoyè.",
      "english": "On the Xiang waters, boat shadows flicker."
    }
  ]
}
