{
  "simplified": "燕麦粥",
  "traditional": "燕麥粥",
  "pinyin": "yànmàizhōu",
  "english": "oatmeal porridge",
  "etymology": {
    "type": "compound word",
    "description": "燕麦(燕麥) (yànmài, \"oats\") + 粥(粥) (zhōu, \"porridge\") refers to a dish made by cooking oats into a thick, warm porridge.",
    "interpretation": "燕麦粥(燕麥粥) (yànmàizhōu, \"oatmeal porridge\") combines the concept of oats and porridge to specify a type of porridge made with oats, commonly consumed as a breakfast dish.",
    "simplification": ""
  },
  "parts": [
    {
      "char": "燕麦",
      "trad": "燕麥",
      "pinyin": "yànmài",
      "english": "oats"
    },
    {
      "char": "粥",
      "trad": "粥",
      "pinyin": "zhōu",
      "english": "porridge"
    }
  ],
  "in_contemporary_usage": true,
  "examples": [
    {
      "chinese": "我早餐喝燕麦粥(我早餐喝燕麥粥)。",
      "pinyin": "Wǒ zǎocān hē yànmàizhōu.",
      "english": "I drink oatmeal porridge for breakfast."
    },
    {
      "chinese": "妈妈做燕麦粥(媽媽做燕麥粥)，味道鲜美(味道鮮美)。",
      "pinyin": "Māmā zuò yànmàizhōu, wèidào xiānměi.",
      "english": "Mom makes oatmeal porridge, and it tastes delicious."
    },
    {
      "chinese": "冬天早晨常喝燕麦粥(冬天早晨常喝燕麥粥)，能暖胃驱寒(能暖胃驅寒)。",
      "pinyin": "Dōngtiān zǎochén cháng hē yànmàizhōu, néng nuǎn wèi qū hán.",
      "english": "Drinking oatmeal porridge on a winter morning can warm the stomach and fend off the cold."
    }
  ]
}
