{
  "simplified": "璜",
  "traditional": "璜",
  "pinyin": "huáng",
  "english": "semicircular jade",
  "etymology": {
    "type": "phono-semantic compound",
    "description": "semantic: 𤣩(\"jade\") + phonetic: 黃(黃) (huáng, \"yellow\") = jade with similar sound to 黃 -> semicircular jade",
    "interpretation": "The character 璜 combines the jade radical 𤣩, indicating its material nature, with 黃(黃) (huáng, \"yellow\") as the phonetic component, indicating the pronunciation. This suggests a type of jade named for its yellowish hue or associated value.",
    "simplification": ""
  },
  "parts": [
    {
      "char": "𤣩",
      "trad": "𤣩",
      "pinyin": "yù",
      "english": "jade"
    },
    {
      "char": "黃",
      "trad": "黃",
      "pinyin": "huáng",
      "english": "yellow"
    }
  ],
  "in_contemporary_usage": false,
  "examples": []
}
