{
  "simplified": "皋",
  "traditional": "皋",
  "pinyin": "gāo",
  "english": "marsh",
  "etymology": {
    "type": "ideogrammic compound",
    "description": "白(白) (bái, \"white, bright\") + 夲(夲) (tuō, \"to advance\") = unclear connection to modern meaning of marsh",
    "interpretation": "The components suggest a bright land advancing or reaching out, although the exact connection to 'marsh' is ambiguous.",
    "simplification": ""
  },
  "parts": [
    {
      "char": "白",
      "trad": "白",
      "pinyin": "bái",
      "english": "white; bright"
    },
    {
      "char": "夲",
      "trad": "夲",
      "pinyin": "tuō",
      "english": "to advance"
    }
  ],
  "in_contemporary_usage": false,
  "examples": []
}
