{
  "simplified": "Áĺē",
  "traditional": "Áĺē",
  "pinyin": "y√†ng",
  "english": "river",
  "etymology": {
    "type": "phono-semantic compound",
    "description": "Phonetic: Áĺä(Áĺä) (y√°ng, \"sheep\") + Semantic: śįł(śįł) (y«íng, \"eternal\") = river",
    "interpretation": "The character Áĺē is a phono-semantic compound where Áĺä(Áĺä) provides the phonetic component, suggesting the pronunciation, and śįł(śįł) adds the semantic aspect, related to water or fluidity, giving the meaning of \"river.\"",
    "simplification": ""
  },
  "parts": [
    {
      "char": "Áĺä",
      "trad": "Áĺä",
      "pinyin": "y√°ng",
      "english": "sheep"
    },
    {
      "char": "śįł",
      "trad": "śįł",
      "pinyin": "y«íng",
      "english": "eternal"
    }
  ],
  "in_contemporary_usage": false,
  "examples": []
}
