{
  "simplified": "้พฐ",
  "traditional": "้พฐ",
  "pinyin": "yรน",
  "english": "stylized feet",
  "etymology": {
    "type": "pictogram",
    "description": "Depicts a stylized foot (้พฐ), originally a footprint pointing up",
    "interpretation": "้พฐ(yรน, \"stylized feet\") presents a stylized representation of a foot, initially picturing a footprint directed upwards with three toes akin to simplified human hand representations. This visualization connects it to other ancient forms depicting extremities, with a particular parallel to the lower extremities depicted by characters like ๆญข(ๆญข) (zhว, \"foot\") as well as other related figures in the oracle script.",
    "simplification": ""
  },
  "parts": [
    {
      "char": "ๆญข",
      "trad": "ๆญข",
      "pinyin": "zhว",
      "english": "foot"
    }
  ],
  "in_contemporary_usage": false,
  "examples": []
}
